consola_io
sasm
sboot
sreset
ssim
toolchain_simplez
vmem
