Metadata-Version: 1.1
Name: toolchain-simplez
Version: 0.0.12
Summary: 
